refinery/__init__.py
refinery/cli.py
kern_refinery-1.3.0.dist-info/LICENSE
kern_refinery-1.3.0.dist-info/METADATA
kern_refinery-1.3.0.dist-info/WHEEL
kern_refinery-1.3.0.dist-info/entry_points.txt
kern_refinery-1.3.0.dist-info/top_level.txt
kern_refinery-1.3.0.dist-info/RECORD
