Metadata-Version: 2.1
Name: kern-refinery
Version: 1.3.0
Summary: The open-source data-centric IDE for NLP.
Home-page: https://github.com/code-kern-ai/refinery
Author: jhoetter
Author-email: johannes.hoetter@kern.ai
License: UNKNOWN
Keywords: Kern AI,refinery,machine-learning,supervised-learning,data-centric-ai,data-annotation,python
Platform: UNKNOWN
Classifier: Development Status :: 4 - Beta
Classifier: Programming Language :: Python :: 3
Classifier: License :: OSI Approved :: Apache Software License
License-File: LICENSE
Requires-Dist: requests
Requires-Dist: wasabi
Requires-Dist: GitPython
